SimpleSchemaGenerator/EntryPoint.py
SimpleSchemaGenerator/Errors.py
SimpleSchemaGenerator/__init__.py
SimpleSchemaGenerator/py.typed
SimpleSchemaGenerator/Common/Error.py
SimpleSchemaGenerator/Common/Location.py
SimpleSchemaGenerator/Common/Region.py
SimpleSchemaGenerator/Common/__init__.py
SimpleSchemaGenerator/SampleSchemas/Cardinality.SimpleSchema
SimpleSchemaGenerator/SampleSchemas/Empty.SimpleSchema
SimpleSchemaGenerator/SampleSchemas/Expressions.SimpleSchema
SimpleSchemaGenerator/SampleSchemas/Extensions.SimpleSchema
SimpleSchemaGenerator/SampleSchemas/Import.SimpleSchema
SimpleSchemaGenerator/SampleSchemas/Miscellaneous.SimpleSchema
SimpleSchemaGenerator/SampleSchemas/Structures.SimpleSchema
SimpleSchemaGenerator/SampleSchemas/Tabs.SimpleSchema
SimpleSchemaGenerator/SampleSchemas/Tuples.SimpleSchema
SimpleSchemaGenerator/SampleSchemas/Variants.SimpleSchema
SimpleSchemaGenerator/Schema/__init__.py
SimpleSchemaGenerator/Schema/Elements/__init__.py
SimpleSchemaGenerator/Schema/Elements/Common/Cardinality.py
SimpleSchemaGenerator/Schema/Elements/Common/Element.py
SimpleSchemaGenerator/Schema/Elements/Common/Metadata.py
SimpleSchemaGenerator/Schema/Elements/Common/TerminalElement.py
SimpleSchemaGenerator/Schema/Elements/Common/UniqueNameTrait.py
SimpleSchemaGenerator/Schema/Elements/Common/Visibility.py
SimpleSchemaGenerator/Schema/Elements/Common/__init__.py
SimpleSchemaGenerator/Schema/Elements/Expressions/BooleanExpression.py
SimpleSchemaGenerator/Schema/Elements/Expressions/Expression.py
SimpleSchemaGenerator/Schema/Elements/Expressions/IntegerExpression.py
SimpleSchemaGenerator/Schema/Elements/Expressions/ListExpression.py
SimpleSchemaGenerator/Schema/Elements/Expressions/NoneExpression.py
SimpleSchemaGenerator/Schema/Elements/Expressions/NumberExpression.py
SimpleSchemaGenerator/Schema/Elements/Expressions/StringExpression.py
SimpleSchemaGenerator/Schema/Elements/Expressions/TupleExpression.py
SimpleSchemaGenerator/Schema/Elements/Expressions/__init__.py
simpleschemagenerator-0.12.7.dist-info/METADATA
simpleschemagenerator-0.12.7.dist-info/WHEEL
simpleschemagenerator-0.12.7.dist-info/licenses/LICENSE
simpleschemagenerator-0.12.7.dist-info/RECORD
