Metadata-Version: 2.4
Name: SimpleSchemaGenerator
Version: 0.12.7
Summary: Add your description here
Project-URL: Homepage, https://github.com/davidbrownell/SimpleSchemaGenerator
Project-URL: Documentation, https://github.com/davidbrownell/SimpleSchemaGenerator
Project-URL: Repository, https://github.com/davidbrownell/SimpleSchemaGenerator
Author-email: David Brownell <github@DavidBrownell.com>
License: MIT
License-File: LICENSE
Classifier: Operating System :: MacOS
Classifier: Operating System :: Microsoft :: Windows
Classifier: Operating System :: POSIX :: Linux
Classifier: Programming Language :: Python
Classifier: Programming Language :: Python :: 3.13
Requires-Python: >=3.13
Requires-Dist: antlr-denter>=1.3.1
Requires-Dist: dbrownell-common>=0.14.6
Requires-Dist: emoji>=2.14.1
Requires-Dist: typer>=0.15.3
